LICENSE.txt
MANIFEST.in
README.md
requirements-tests.txt
requirements.txt
setup.py
django_select2light.egg-info/PKG-INFO
django_select2light.egg-info/SOURCES.txt
django_select2light.egg-info/dependency_links.txt
django_select2light.egg-info/not-zip-safe
django_select2light.egg-info/requires.txt
django_select2light.egg-info/top_level.txt
select2light/__init__.py
select2light/models.py
select2light/tests.py
select2light/tests_urls.py
select2light/urls.py
select2light/views.py
select2light/widgets.py
select2light/static/jquery-1.7.2.min.js
select2light/static/select2-3.3.2/README.md
select2light/static/select2-3.3.2/component.json
select2light/static/select2-3.3.2/release.sh
select2light/static/select2-3.3.2/select2-spinner.gif
select2light/static/select2-3.3.2/select2.css
select2light/static/select2-3.3.2/select2.jquery.json
select2light/static/select2-3.3.2/select2.js
select2light/static/select2-3.3.2/select2.png
select2light/static/select2-3.3.2/select2_locale_de.js
select2light/static/select2-3.3.2/select2_locale_en.js.template
select2light/static/select2-3.3.2/select2_locale_es.js
select2light/static/select2-3.3.2/select2_locale_eu.js
select2light/static/select2-3.3.2/select2_locale_fr.js
select2light/static/select2-3.3.2/select2_locale_hr.js
select2light/static/select2-3.3.2/select2_locale_hu.js
select2light/static/select2-3.3.2/select2_locale_it.js
select2light/static/select2-3.3.2/select2_locale_nl.js
select2light/static/select2-3.3.2/select2_locale_pt-BR.js
select2light/static/select2-3.3.2/select2_locale_pt-PT.js
select2light/static/select2-3.3.2/select2_locale_ro.js
select2light/static/select2-3.3.2/select2_locale_ru.js
select2light/static/select2-3.3.2/select2_locale_sk.js
select2light/static/select2-3.3.2/select2_locale_sv.js
select2light/static/select2-3.3.2/select2_locale_tr.js
select2light/static/select2-3.3.2/select2_locale_ua.js
select2light/static/select2-3.3.2/select2_locale_zh-CN.js
select2light/static/select2-3.3.2/select2x2.png
select2light/templates/select2light/ajax_select2.html
select2light/templates/select2light/select2.html
testapp/manage.py
testapp/testapp/__init__.py
testapp/testapp/settings.py
testapp/testapp/urls.py
testapp/testapp/wsgi.py
testapp/testapp/templates/500.html
