Metadata-Version: 1.0
Name: django-select2light
Version: 0.3
Summary: Select2 widget 'light edition' for Django projects
Home-page: https://github.com/ouhouhsami/django-select2light
Author: Samuel Goldszmidt
Author-email: samuel.goldszmidt@gmail.com
License: Apache License 2.0
Platform: UNKNOWN
Classifier: Development Status :: 3 - Alpha
Classifier: Environment :: Web Environment
Classifier: Intended Audience :: Developers
Classifier: License :: OSI Approved :: Apache Software License
Classifier: Operating System :: OS Independent
Classifier: Programming Language :: Python
Classifier: Framework :: Django
